setup.cfg
setup.py
SDF/__init__.py
SDF/config_loader.py
SDF/sdf_base.py
SDF/sdf_comment.py
SDF/sdf_data.py
SDF/sdf_data_img.py
SDF/sdf_data_mc.py
SDF/sdf_data_sc.py
SDF/sdf_date.py
SDF/sdf_enc_string.py
SDF/sdf_gen_val.py
SDF/sdf_instrument.py
SDF/sdf_name.py
SDF/sdf_object.py
SDF/sdf_owner.py
SDF/sdf_par.py
SDF/sdf_rc.py
SDF/sdf_sample.py
SDF/sdf_string.py
SDF/sdf_utils.py
SDF/xml_string_helper.py
SDF/CLI/__init__.py
SDF/CLI/cli_base.py
SDF/CLI/sdf_convert_jpk2sdf.py
SDF/CLI/sdf_convert_lsm2sdf.py
SDF/CLI/sdf_convert_mfp2sdf.py
SDF/CLI/sdf_convert_oib2sdf.py
SDF/CLI/sdf_convert_oif2sdf.py
SDF/CLI/sdf_convert_sdf2forcesdf.py
SDF/GUI/__init__.py
SDF/GUI/qt_xml_sdf_handler.py
SDF/GUI/sdf_browser.py
SDF/GUI/controller/__init__.py
SDF/GUI/controller/browser_controller.py
SDF/GUI/controller/data_preview_widget_controller.py
SDF/GUI/controller/plot_preview_widget_controller.py
SDF/GUI/controller/summary_widget_controller.py
SDF/GUI/model/__init__.py
SDF/GUI/model/qt_sdf_model.py
SDF/GUI/model/qt_sdf_parameter_model.py
SDF/GUI/view/__init__.py
SDF/GUI/view/browser.py
SDF/GUI/view/customtreeview.py
SDF/GUI/view/data_preview_widget.py
SDF/GUI/view/htmldelegate.py
SDF/GUI/view/plot_preview_widget.py
SDF/GUI/view/sdf_parameters_browser.py
SDF/GUI/view/styles.py
SDF/GUI/view/summary_widget.py
SDF/convert/__init__.py
SDF/convert/_helper_functions.py
SDF/convert/forcesdf2mat.py
SDF/convert/jpk2sdf.py
SDF/convert/lsm2sdf.py
SDF/convert/mfp2sdf.py
SDF/convert/oif2sdf.py
SDF/convert/sdf2forcesdf.py
SDF/extern/__init__.py
SDF/extern/_setup_for_tifffile_C_extension.py
SDF/extern/jpkfile.py
SDF/extern/mfpfile.py
SDF/extern/oiffile.py
SDF/extern/png.py
SDF/extern/tifffile.py
SDF/file_io/__init__.py
SDF/file_io/sdf_inspect.py
SDF/file_io/sdf_load.py
SDF/sdf_wrapper/__init__.py
SDF/sdf_wrapper/sdf_force.py
SDF/sdf_wrapper/sdf_par_source.py
sdformat.egg-info/PKG-INFO
sdformat.egg-info/SOURCES.txt
sdformat.egg-info/dependency_links.txt
sdformat.egg-info/entry_points.txt
sdformat.egg-info/not-zip-safe
sdformat.egg-info/requires.txt
sdformat.egg-info/top_level.txt