Metadata-Version: 1.0
Name: sdformat
Version: 0.23.2
Summary: Python Interface of a Standard Data Format
Home-page: UNKNOWN
Author: Burkhard Geil, Filip Savic, Ilyas Kuhlemann
Author-email: ilyasp.ku@gmail.com
License: GNU GPLv3
Platform: UNKNOWN
